ngutils/__init__.py
ngutils/functions.py
ngutils-0.10.1.dist-info/LICENSE
ngutils-0.10.1.dist-info/METADATA
ngutils-0.10.1.dist-info/WHEEL
ngutils-0.10.1.dist-info/top_level.txt
ngutils-0.10.1.dist-info/RECORD
