Metadata-Version: 2.1
Name: ngutils
Version: 0.10.1
Summary: Some useful ETL, EDA & other features
Home-page: https://github.com/nigani/ngutils
Author: nigani
Author-email: nigani@internet.ru
License: GNU GPL v3
Platform: UNKNOWN
License-File: LICENSE
Requires-Dist: pandas (>=1.1.0)
Requires-Dist: requests (>=2.24.0)
Requires-Dist: lxml (>=4.5.2)
Requires-Dist: tqdm (>=4.50.0)
